<?xml version="1.0" encoding="UTF-8"?>
<metadata xml:lang="sv"><Esri><CreaDate>20190105</CreaDate><CreaTime>15273800</CreaTime><ArcGISFormat>1.0</ArcGISFormat><SyncOnce>TRUE</SyncOnce><DataProperties><itemProps><itemLocation><linkage Sync="TRUE">file://\\dustaff\home\xzh\Documents\My Document\Courses Document\MI3001-Spatial Data and GIS\My Lectures\Other data\Kommuner_Sverige</linkage><protocol Sync="TRUE">Local Area Network</protocol></itemLocation></itemProps><copyHistory><copy source="\\dustaff\home\xzh\Documents\My Document\Courses Document\IK1056- Introduktion till Geografiska Informations System (GIS)\Tentamen_IK1056_20160527_Del3\Tentamen_IK1056_20160527_Del3\Tentamen_IK1056_20160527_Del3\Kommuner_Sverige" dest="\\dustaff\home\xzh\Documents\My Document\Courses Document\MI3001-Spatial Data and GIS\My Lectures\Other data\Kommuner_Sverige" date="20161216" time="19302300"></copy></copyHistory><lineage><Process ToolSource="c:\program files (x86)\arcgis\desktop10.5\ArcToolbox\Toolboxes\Data Management Tools.tbx\Project" Date="20190105" Time="152739">Project Kommuner_Sverige "\\dustudent\home\v10frajo\Documents\ArcGIS\Final Project\Task2\Kommuner_Sverige.shp" PROJCS['RT90_25_gon_V',GEOGCS['GCS_RT_1990',DATUM['D_RT_1990',SPHEROID['Bessel_1841',6377397.155,299.1528128]],PRIMEM['Greenwich',0.0],UNIT['Degree',0.0174532925199433]],PROJECTION['Transverse_Mercator'],PARAMETER['False_Easting',1500000.0],PARAMETER['False_Northing',0.0],PARAMETER['Central_Meridian',15.80827777777778],PARAMETER['Scale_Factor',1.0],PARAMETER['Latitude_Of_Origin',0.0],UNIT['Meter',1.0]] # PROJCS['RT90_25_gon_V',GEOGCS['GCS_RT_1990',DATUM['D_RT_1990',SPHEROID['Bessel_1841',6377397.155,299.1528128]],PRIMEM['Greenwich',0.0],UNIT['Degree',0.0174532925199433]],PROJECTION['Transverse_Mercator'],PARAMETER['False_Easting',1500000.0],PARAMETER['False_Northing',0.0],PARAMETER['Central_Meridian',15.80827777777778],PARAMETER['Scale_Factor',1.0],PARAMETER['Latitude_Of_Origin',0.0],UNIT['Meter',1.0]] NO_PRESERVE_SHAPE # NO_VERTICAL</Process></lineage></DataProperties></Esri></metadata>
